dccutils_server/__init__.py
dccutils_server/__version__.py
dccutils_server/api.py
dccutils_server/server.py
dccutils_server-0.1.3.dist-info/LICENSE
dccutils_server-0.1.3.dist-info/METADATA
dccutils_server-0.1.3.dist-info/WHEEL
dccutils_server-0.1.3.dist-info/top_level.txt
dccutils_server-0.1.3.dist-info/RECORD
