Metadata-Version: 2.1
Name: dccutils-server
Version: 0.1.3
Summary: dccutils_server is a fastAPI server for DCCs based on dccutils.
Home-page: https://gazu.cg-wire.com/
Author: CG Wire
Author-email: evan@cg-wire.com
License: GNU Library or Lesser General Public License (LGPL)
Keywords: fastapi,dcc,cg,production
Platform: UNKNOWN
Classifier: Development Status :: 5 - Production/Stable
Classifier: Environment :: Web Environment
Classifier: Intended Audience :: Developers
Classifier: Natural Language :: English
Classifier: Programming Language :: Python :: 3.6
Classifier: Programming Language :: Python :: 3.7
Classifier: Programming Language :: Python :: 3.8
Classifier: Programming Language :: Python :: 3.9
Classifier: Programming Language :: Python :: 3.10
Classifier: Programming Language :: Python :: Implementation :: CPython
Classifier: Programming Language :: Python :: Implementation :: PyPy
Classifier: Topic :: Multimedia :: Graphics
Requires-Python: >=3.7
License-File: LICENSE
Requires-Dist: dccutils (==0.1.8)
Requires-Dist: fastapi (==0.85.0)
Requires-Dist: uvicorn (==0.18.3)
Provides-Extra: dev
Requires-Dist: wheel ; extra == 'dev'
Provides-Extra: test
Requires-Dist: pre-commit (<=2.20.0) ; extra == 'test'
Requires-Dist: black (<=22.8.0) ; (python_version >= "3.5") and extra == 'test'
